mongo_api/__init__.py
mongo_api/client.py
mongo_api/test_api.py
mongo_api/utils.py
mongo_api_yunsou-0.1.3.dist-info/LICENSE
mongo_api_yunsou-0.1.3.dist-info/METADATA
mongo_api_yunsou-0.1.3.dist-info/WHEEL
mongo_api_yunsou-0.1.3.dist-info/top_level.txt
mongo_api_yunsou-0.1.3.dist-info/RECORD
