Metadata-Version: 2.1
Name: mongo-api-yunsou
Version: 0.1.3
Summary: A database api for inserting, searching, updating and deleting based on mongdb
Home-page: https://github.com/pypa/sampleproject
Author: sysuyanxp
Author-email: yanxp3@mail2.sysu.edu.cn
License: UNKNOWN
Platform: UNKNOWN
Classifier: Programming Language :: Python :: 3
Classifier: License :: OSI Approved :: MIT License
Classifier: Operating System :: OS Independent
Requires-Python: >=3.6
